topsis/__init__.py
topsis/minal102203788.py
Topsis_Minal_102203788-0.1.dist-info/METADATA
Topsis_Minal_102203788-0.1.dist-info/WHEEL
Topsis_Minal_102203788-0.1.dist-info/entry_points.txt
Topsis_Minal_102203788-0.1.dist-info/top_level.txt
Topsis_Minal_102203788-0.1.dist-info/RECORD
