Metadata-Version: 2.2
Name: Topsis-Minal-102203788
Version: 0.1
Summary: A Python package to implement the Topsis method for decision-making
Home-page: https://github.com/minal2577/Topsis-Minal-102203788
Author: Minal
Author-email: mminal_be22@thapar.edu
Classifier: Programming Language :: Python :: 3
Classifier: License :: OSI Approved :: MIT License
Requires-Dist: pandas
Requires-Dist: numpy
Requires-Dist: sys
Dynamic: author
Dynamic: author-email
Dynamic: classifier
Dynamic: description
Dynamic: description-content-type
Dynamic: home-page
Dynamic: requires-dist
Dynamic: summary
